azure/mgmt/voiceservices/__init__.py
azure/mgmt/voiceservices/_configuration.py
azure/mgmt/voiceservices/_patch.py
azure/mgmt/voiceservices/_serialization.py
azure/mgmt/voiceservices/_vendor.py
azure/mgmt/voiceservices/_version.py
azure/mgmt/voiceservices/_voice_services_mgmt_client.py
azure/mgmt/voiceservices/py.typed
azure/mgmt/voiceservices/aio/__init__.py
azure/mgmt/voiceservices/aio/_configuration.py
azure/mgmt/voiceservices/aio/_patch.py
azure/mgmt/voiceservices/aio/_voice_services_mgmt_client.py
azure/mgmt/voiceservices/aio/operations/__init__.py
azure/mgmt/voiceservices/aio/operations/_communications_gateways_operations.py
azure/mgmt/voiceservices/aio/operations/_name_availability_operations.py
azure/mgmt/voiceservices/aio/operations/_operations.py
azure/mgmt/voiceservices/aio/operations/_patch.py
azure/mgmt/voiceservices/aio/operations/_test_lines_operations.py
azure/mgmt/voiceservices/models/__init__.py
azure/mgmt/voiceservices/models/_models_py3.py
azure/mgmt/voiceservices/models/_patch.py
azure/mgmt/voiceservices/models/_voice_services_mgmt_client_enums.py
azure/mgmt/voiceservices/operations/__init__.py
azure/mgmt/voiceservices/operations/_communications_gateways_operations.py
azure/mgmt/voiceservices/operations/_name_availability_operations.py
azure/mgmt/voiceservices/operations/_operations.py
azure/mgmt/voiceservices/operations/_patch.py
azure/mgmt/voiceservices/operations/_test_lines_operations.py
azure_mgmt_voiceservices-1.0.0.dist-info/LICENSE
azure_mgmt_voiceservices-1.0.0.dist-info/METADATA
azure_mgmt_voiceservices-1.0.0.dist-info/WHEEL
azure_mgmt_voiceservices-1.0.0.dist-info/top_level.txt
azure_mgmt_voiceservices-1.0.0.dist-info/RECORD
